Workbook

Sheet settings
A1: Settings
A2: Yellow cells are inputs. Every price in this workbook is a formula on these cells and on the 247_base sheet.
A4: Setting | B4: Value | C4: Note
A5: markup_vs_247 | B5: 0.1 | C5: StretchMetal sells at 247TailorSteel × (1 + markup)
A6: target_margin_on_revenue | B6: 0.3 | C6: Required margin on revenue; cost_at_margin columns = sell × (1 − this)
A7: rate_version_name | B7: market-247+10% v1 (26 Sep 2026) | C7: Name for the new row in rate_versions
A8: currency | B8: EUR | C8: All values EUR ex VAT
A9: base_lead_time_working_days | B9: 11 | C9: 247 standard delivery used as the base (12 Oct 2026 quotes)
A10: test_cut_density_m_per_dm2 | B10: 0.2265 | C10: Cut length per dm² of the two parts used per material group (SQ100 → H04xD20 step); used to split the combined €/dm² into area / cut / pierce
A11: test_pierces_per_dm2 | B11: 1.392 | C11: Pierces per dm² of the same step

Sheet 247_base
A1: 247TailorSteel base rates (12 Oct 2026 delivery, qty 1, pickup) — fitted from quotes BE26065398/399/400
A2: Blue = fitted or measured; black = formula. DC01 1.5 is a joint fit of 49 prices; other groups come from two parts each (±10–20 %). Cut and pierce rates of the other groups are scaled from DC01 1.5 by machine time (assumption, editable).
A4: material_code | B4: thickness_mm | C4: gas | D4: setup per material/thickness (€) | E4: combined €/dm² net (incl. cutting) | F4: speed m/min (tool table) | G4: pierce s (tool table) | H4: cut €/m | I4: pierce € | J4: area-only €/dm² | K4: kg per dm² | L4: note
A5: DC01 | B5: 1 | C5: N2 | D5: 49.39 | E5: 0.609 | F5: 25 | G5: 0.2 | H5: =$H$6*$F$6/F5 -> 0.17794 | I5: =$I$6*G5/$G$6 -> 0.0168 | J5: =E5-settings!$B$10*H5-settings!$B$11*I5 -> 0.54531099 | K5: =B5*7850/100000 -> 0.0785 | L5: Two-part group; cut €/m ∝ 1/speed and pierce € ∝ pierce time vs DC01 1.5 (assumption); area = combined − cut − pierce share
A6: DC01 | B6: 1.5 | C6: N2 | D6: 33.93 | E6: 0.455 | F6: 20.5 | G6: 0.25 | H6: 0.217 | I6: 0.021 | J6: 0.377 | K6: =B6*7850/100000 -> 0.11775 | L6: Joint fit: area, cut and pierce fitted separately (RMSE €0.26)
A7: DC01 | B7: 2 | C7: N2 | D7: 31.16 | E7: 0.894 | F7: 16 | G7: 0.3 | H7: =$H$6*$F$6/F7 -> 0.27803125 | I7: =$I$6*G7/$G$6 -> 0.0252 | J7: =E7-settings!$B$10*H7-settings!$B$11*I7 -> 0.79594752 | K7: =B7*7850/100000 -> 0.157 | L7: Two-part group; cut €/m ∝ 1/speed and pierce € ∝ pierce time vs DC01 1.5 (assumption); area = combined − cut − pierce share
A8: DC01 | B8: 3 | C8: O2 | D8: 36.07 | E8: 1.096 | F8: 11 | G8: 0.4 | H8: =$H$6*$F$6/F8 -> 0.40440909 | I8: =$I$6*G8/$G$6 -> 0.0336 | J8: =E8-settings!$B$10*H8-settings!$B$11*I8 -> 0.95763014 | K8: =B8*7850/100000 -> 0.2355 | L8: Two-part group; cut €/m ∝ 1/speed and pierce € ∝ pierce time vs DC01 1.5 (assumption); area = combined − cut − pierce share
A9: S235 | B9: 3 | C9: O2 | D9: 29.1 | E9: 1.134 | F9: 11 | G9: 0.4 | H9: =$H$6*$F$6/F9 -> 0.40440909 | I9: =$I$6*G9/$G$6 -> 0.0336 | J9: =E9-settings!$B$10*H9-settings!$B$11*I9 -> 0.99563014 | K9: =B9*7850/100000 -> 0.2355 | L9: Two-part group; cut €/m ∝ 1/speed and pierce € ∝ pierce time vs DC01 1.5 (assumption); area = combined − cut − pierce share
A10: S235 | B10: 5 | C10: O2 | D10: 25.54 | E10: 1.472 | F10: 5.5 | G10: 0.8 | H10: =$H$6*$F$6/F10 -> 0.80881818 | I10: =$I$6*G10/$G$6 -> 0.0672 | J10: =E10-settings!$B$10*H10-settings!$B$11*I10 -> 1.1952603 | K10: =B10*7850/100000 -> 0.3925 | L10: Two-part group; cut €/m ∝ 1/speed and pierce € ∝ pierce time vs DC01 1.5 (assumption); area = combined − cut − pierce share
A11: S235 | B11: 8 | C11: O2 | D11: 26.71 | E11: 2.606 | F11: 3 | G11: 1.3 | H11: =$H$6*$F$6/F11 -> 1.4828333 | I11: =$I$6*G11/$G$6 -> 0.1092 | J11: =E11-settings!$B$10*H11-settings!$B$11*I11 -> 2.1181319 | K11: =B11*7850/100000 -> 0.628 | L11: Two-part group; cut €/m ∝ 1/speed and pierce € ∝ pierce time vs DC01 1.5 (assumption); area = combined − cut − pierce share
A12: S235 | B12: 10 | C12: O2 | D12: 21.73 | E12: 2.989 | F12: 2.2 | G12: 1.6 | H12: =$H$6*$F$6/F12 -> 2.0220455 | I12: =$I$6*G12/$G$6 -> 0.1344 | J12: =E12-settings!$B$10*H12-settings!$B$11*I12 -> 2.3439219 | K12: =B12*7850/100000 -> 0.785 | L12: Two-part group; cut €/m ∝ 1/speed and pierce € ∝ pierce time vs DC01 1.5 (assumption); area = combined − cut − pierce share
A13: 1.4301 | B13: 1.5 | C13: N2 | D13: 32.24 | E13: 1.753 | F13: 14.35 | G13: 0.25 | H13: =$H$6*$F$6/F13 -> 0.31 | I13: =$I$6*G13/$G$6 -> 0.021 | J13: =E13-settings!$B$10*H13-settings!$B$11*I13 -> 1.653553 | K13: =B13*7900/100000 -> 0.1185 | L13: Two-part group; cut €/m ∝ 1/speed and pierce € ∝ pierce time vs DC01 1.5 (assumption); area = combined − cut − pierce share
A14: AlMg3 | B14: 1.5 | C14: N2 | D14: 50.12 | E14: 1.6 | F14: 14.35 | G14: 0.25 | H14: =$H$6*$F$6/F14 -> 0.31 | I14: =$I$6*G14/$G$6 -> 0.021 | J14: =E14-settings!$B$10*H14-settings!$B$11*I14 -> 1.500553 | K14: =B14*2660/100000 -> 0.0399 | L14: Two-part group; cut €/m ∝ 1/speed and pierce € ∝ pierce time vs DC01 1.5 (assumption); area = combined − cut − pierce share
A16: item | B16: value | L16: note
A17: order_charge_eur | B17: 16.26 | L17: Per order, shared by all part lines
A18: deburr_setup_per_order_eur | B18: 33.48 | L18: Edge breaking both sides: shared by the edge-broken lines
A19: deburr_per_m_eur | B19: 1.173 | L19: per m of cut length of the edge-broken part
A20: engrave_per_part_eur | B20: 0.38 | L20: Part name engraved
A21: packaging_box_eur | B21: 2.5 | L21: Small order (test 1)
A22: packaging_pallet_eur | B22: 31.3 | L22: Average of €29.11 (test 2) and €33.44 (test 3)
A23: leadtime_mult_11wd | B23: 1 | L23: 12 Oct = base
A24: leadtime_mult_7wd | B24: 1.14 | L24: 6 Oct: €592.72 / €519.74 (test 3)
A25: leadtime_mult_4wd | B25: 1.711 | L25: 1 Oct: €889.04 / €519.74 (test 3)

Sheet materials_price_bands
A1: materials.price_per_kg — selling price per kg of NET part mass (holes credited), by thickness band
A2: Import as the price_per_kg JSON bands [{maxThicknessMm, pricePerKg}] of each material; set scrap_pct_default = 0 and price on net mass (geometry.massKg), not on the blank rectangle.
A4: material_code | B4: max_thickness_mm | C4: price_per_kg_sell (€) | D4: price_per_kg_cost_at_margin (€) | E4: 247 area-only €/dm² (base) | F4: source | G4: note
A5: DC01 | B5: 1 | C5: =247_base!$J$5*(1+settings!$B$5)/247_base!$K$5 -> 7.6413005 | D5: =C5*(1-settings!$B$6) -> 5.3489103 | E5: =247_base!$J$5 -> 0.54531099 | F5: tested | G5: €/kg = area-only €/dm² × (1+markup) ÷ kg per dm² at that thickness — so the €/kg changes with thickness, as 247 does
A6: DC01 | B6: 1.5 | C6: =247_base!$J$6*(1+settings!$B$5)/247_base!$K$6 -> 3.5218684 | D6: =C6*(1-settings!$B$6) -> 2.4653079 | E6: =247_base!$J$6 -> 0.377 | F6: tested (joint fit) | G6: €/kg = area-only €/dm² × (1+markup) ÷ kg per dm² at that thickness — so the €/kg changes with thickness, as 247 does
A7: DC01 | B7: 2 | C7: =247_base!$J$7*(1+settings!$B$5)/247_base!$K$7 -> 5.5767024 | D7: =C7*(1-settings!$B$6) -> 3.9036917 | E7: =247_base!$J$7 -> 0.79594752 | F7: tested | G7: €/kg = area-only €/dm² × (1+markup) ÷ kg per dm² at that thickness — so the €/kg changes with thickness, as 247 does
A8: DC01 | B8: 3 | C8: =247_base!$J$8*(1+settings!$B$5)/247_base!$K$8 -> 4.473007 | D8: =C8*(1-settings!$B$6) -> 3.1311049 | E8: =247_base!$J$8 -> 0.95763014 | F8: tested | G8: €/kg = area-only €/dm² × (1+markup) ÷ kg per dm² at that thickness — so the €/kg changes with thickness, as 247 does
A9: S235 | B9: 3 | C9: =247_base!$J$9*(1+settings!$B$5)/247_base!$K$9 -> 4.6505017 | D9: =C9*(1-settings!$B$6) -> 3.2553512 | E9: =247_base!$J$9 -> 0.99563014 | F9: tested | G9: €/kg = area-only €/dm² × (1+markup) ÷ kg per dm² at that thickness — so the €/kg changes with thickness, as 247 does
A10: S235 | B10: 5 | C10: =247_base!$J$10*(1+settings!$B$5)/247_base!$K$10 -> 3.349774 | D10: =C10*(1-settings!$B$6) -> 2.3448418 | E10: =247_base!$J$10 -> 1.1952603 | F10: tested | G10: €/kg = area-only €/dm² × (1+markup) ÷ kg per dm² at that thickness — so the €/kg changes with thickness, as 247 does
A11: S235 | B11: 8 | C11: =247_base!$J$11*(1+settings!$B$5)/247_base!$K$11 -> 3.7101036 | D11: =C11*(1-settings!$B$6) -> 2.5970725 | E11: =247_base!$J$11 -> 2.1181319 | F11: tested | G11: €/kg = area-only €/dm² × (1+markup) ÷ kg per dm² at that thickness — so the €/kg changes with thickness, as 247 does
A12: S235 | B12: 999 | C12: =247_base!$J$12*(1+settings!$B$5)/247_base!$K$12 -> 3.2844766 | D12: =C12*(1-settings!$B$6) -> 2.2991336 | E12: =247_base!$J$12 -> 2.3439219 | F12: tested at 10 mm; used for 10–12.7 mm until tested | G12: €/kg = area-only €/dm² × (1+markup) ÷ kg per dm² at that thickness — so the €/kg changes with thickness, as 247 does
A13: 1.4301 | B13: 999 | C13: =247_base!$J$13*(1+settings!$B$5)/247_base!$K$13 -> 15.349437 | D13: =C13*(1-settings!$B$6) -> 10.744606 | E13: =247_base!$J$13 -> 1.653553 | F13: tested at 1.5 mm only; other thicknesses untested | G13: €/kg = area-only €/dm² × (1+markup) ÷ kg per dm² at that thickness — so the €/kg changes with thickness, as 247 does
A14: AlMg3 | B14: 999 | C14: =247_base!$J$14*(1+settings!$B$5)/247_base!$K$14 -> 41.368629 | D14: =C14*(1-settings!$B$6) -> 28.95804 | E14: =247_base!$J$14 -> 1.500553 | F14: tested at 1.5 mm only; other thicknesses untested | G14: €/kg = area-only €/dm² × (1+markup) ÷ kg per dm² at that thickness — so the €/kg changes with thickness, as 247 does
A16: Purchase prices to confirm with suppliers (current placeholders in materials table): DC01 €1.05/kg · S235 €1.10 (≤3) / €1.15 (≤8) / €1.20 (>8) · 1.4301 €3.60 · AlMg3 €4.50. The cost_at_margin column is the maximum all-in cost per kg (material + cutting share) for a 30 % margin.

Sheet rate_laser
A1: rate_laser — one row per material × thickness (mode per_m); NEW column setup_eur (shared by the parts of that material/thickness in an order)
A2: Selling rates; the area part of the price sits in materials_price_bands. Rows marked interpolated are not tested in Sophia.
A4: material_code | B4: thickness_mm | C4: gas | D4: mode | E4: speed_m_min | F4: pierce_s | G4: price_per_m_sell (€) | H4: price_per_pierce_sell (€) | I4: setup_eur_sell (€) | J4: price_per_m_cost_at_margin (€) | K4: price_per_pierce_cost_at_margin (€) | L4: setup_eur_cost_at_margin (€) | M4: min_contour_mm | N4: in_house | O4: placeholder | P4: source
A5: DC01 | B5: 1 | C5: N2 | D5: per_m | E5: 25 | F5: 0.2 | G5: =247_base!$H$5*(1+settings!$B$5) -> 0.195734 | H5: =247_base!$I$5*(1+settings!$B$5) -> 0.01848 | I5: =247_base!$D$5*(1+settings!$B$5) -> 54.329 | J5: =G5*(1-settings!$B$6) -> 0.1370138 | K5: =H5*(1-settings!$B$6) -> 0.012936 | L5: =I5*(1-settings!$B$6) -> 38.0303 | M5: 10 | N5: TRUE | O5: FALSE | P5: tested in Sophia (BE26065400)
A6: DC01 | B6: 1.5 | C6: N2 | D6: per_m | E6: 20.5 | F6: 0.25 | G6: =247_base!$H$6*(1+settings!$B$5) -> 0.2387 | H6: =247_base!$I$6*(1+settings!$B$5) -> 0.0231 | I6: =247_base!$D$6*(1+settings!$B$5) -> 37.323 | J6: =G6*(1-settings!$B$6) -> 0.16709 | K6: =H6*(1-settings!$B$6) -> 0.01617 | L6: =I6*(1-settings!$B$6) -> 26.1261 | M6: 15 | N6: TRUE | O6: FALSE | P6: tested (joint fit of 49 prices)
A7: DC01 | B7: 2 | C7: N2 | D7: per_m | E7: 16 | F7: 0.3 | G7: =247_base!$H$7*(1+settings!$B$5) -> 0.30583437 | H7: =247_base!$I$7*(1+settings!$B$5) -> 0.02772 | I7: =247_base!$D$7*(1+settings!$B$5) -> 34.276 | J7: =G7*(1-settings!$B$6) -> 0.21408406 | K7: =H7*(1-settings!$B$6) -> 0.019404 | L7: =I7*(1-settings!$B$6) -> 23.9932 | M7: 20 | N7: TRUE | O7: FALSE | P7: tested in Sophia (BE26065400)
A8: DC01 | B8: 3 | C8: O2 | D8: per_m | E8: 11 | F8: 0.4 | G8: =247_base!$H$8*(1+settings!$B$5) -> 0.44485 | H8: =247_base!$I$8*(1+settings!$B$5) -> 0.03696 | I8: =247_base!$D$8*(1+settings!$B$5) -> 39.677 | J8: =G8*(1-settings!$B$6) -> 0.311395 | K8: =H8*(1-settings!$B$6) -> 0.025872 | L8: =I8*(1-settings!$B$6) -> 27.7739 | M8: 30 | N8: TRUE | O8: FALSE | P8: tested in Sophia (BE26065400)
A9: S235 | B9: 3 | C9: O2 | D9: per_m | E9: 11 | F9: 0.4 | G9: =247_base!$H$9*(1+settings!$B$5) -> 0.44485 | H9: =247_base!$I$9*(1+settings!$B$5) -> 0.03696 | I9: =247_base!$D$9*(1+settings!$B$5) -> 32.01 | J9: =G9*(1-settings!$B$6) -> 0.311395 | K9: =H9*(1-settings!$B$6) -> 0.025872 | L9: =I9*(1-settings!$B$6) -> 22.407 | M9: 30 | N9: TRUE | O9: FALSE | P9: tested in Sophia (BE26065400)
A10: S235 | B10: 5 | C10: O2 | D10: per_m | E10: 5.5 | F10: 0.8 | G10: =247_base!$H$10*(1+settings!$B$5) -> 0.8897 | H10: =247_base!$I$10*(1+settings!$B$5) -> 0.07392 | I10: =247_base!$D$10*(1+settings!$B$5) -> 28.094 | J10: =G10*(1-settings!$B$6) -> 0.62279 | K10: =H10*(1-settings!$B$6) -> 0.051744 | L10: =I10*(1-settings!$B$6) -> 19.6658 | M10: 50 | N10: TRUE | O10: FALSE | P10: tested in Sophia (BE26065400)
A11: S235 | B11: 8 | C11: O2 | D11: per_m | E11: 3 | F11: 1.3 | G11: =247_base!$H$11*(1+settings!$B$5) -> 1.6311167 | H11: =247_base!$I$11*(1+settings!$B$5) -> 0.12012 | I11: =247_base!$D$11*(1+settings!$B$5) -> 29.381 | J11: =G11*(1-settings!$B$6) -> 1.1417817 | K11: =H11*(1-settings!$B$6) -> 0.084084 | L11: =I11*(1-settings!$B$6) -> 20.5667 | M11: 80 | N11: TRUE | O11: FALSE | P11: tested in Sophia (BE26065400)
A12: S235 | B12: 10 | C12: O2 | D12: per_m | E12: 2.2 | F12: 1.6 | G12: =247_base!$H$12*(1+settings!$B$5) -> 2.22425 | H12: =247_base!$I$12*(1+settings!$B$5) -> 0.14784 | I12: =247_base!$D$12*(1+settings!$B$5) -> 23.903 | J12: =G12*(1-settings!$B$6) -> 1.556975 | K12: =H12*(1-settings!$B$6) -> 0.103488 | L12: =I12*(1-settings!$B$6) -> 16.7321 | M12: 100 | N12: TRUE | O12: FALSE | P12: tested in Sophia (BE26065400)
A13: 1.4301 | B13: 1.5 | C13: N2 | D13: per_m | E13: 14.35 | F13: 0.25 | G13: =247_base!$H$13*(1+settings!$B$5) -> 0.341 | H13: =247_base!$I$13*(1+settings!$B$5) -> 0.0231 | I13: =247_base!$D$13*(1+settings!$B$5) -> 35.464 | J13: =G13*(1-settings!$B$6) -> 0.2387 | K13: =H13*(1-settings!$B$6) -> 0.01617 | L13: =I13*(1-settings!$B$6) -> 24.8248 | M13: 15 | N13: TRUE | O13: FALSE | P13: tested in Sophia (BE26065400)
A14: AlMg3 | B14: 1.5 | C14: N2 | D14: per_m | E14: 14.35 | F14: 0.25 | G14: =247_base!$H$14*(1+settings!$B$5) -> 0.341 | H14: =247_base!$I$14*(1+settings!$B$5) -> 0.0231 | I14: =247_base!$D$14*(1+settings!$B$5) -> 55.132 | J14: =G14*(1-settings!$B$6) -> 0.2387 | K14: =H14*(1-settings!$B$6) -> 0.01617 | L14: =I14*(1-settings!$B$6) -> 38.5924 | M14: 15 | N14: TRUE | O14: FALSE | P14: tested in Sophia (BE26065400)
A15: DC01 | B15: 2.5 | C15: N2 | D15: per_m | E15: 13.5 | F15: 0.35 | G15: =G7+((2.5-2)/(3-2))*(G8-G7) -> 0.37534219 | H15: =H7+((2.5-2)/(3-2))*(H8-H7) -> 0.03234 | I15: =I7+((2.5-2)/(3-2))*(I8-I7) -> 36.9765 | J15: =G15*(1-settings!$B$6) -> 0.26273953 | K15: =H15*(1-settings!$B$6) -> 0.022638 | L15: =I15*(1-settings!$B$6) -> 25.88355 | M15: 25 | N15: TRUE | O15: FALSE | P15: interpolated between 2 and 3 mm — not tested
A16: S235 | B16: 4 | C16: O2 | D16: per_m | E16: 7 | F16: 0.6 | G16: =G9+((4-3)/(5-3))*(G10-G9) -> 0.667275 | H16: =H9+((4-3)/(5-3))*(H10-H9) -> 0.05544 | I16: =I9+((4-3)/(5-3))*(I10-I9) -> 30.052 | J16: =G16*(1-settings!$B$6) -> 0.4670925 | K16: =H16*(1-settings!$B$6) -> 0.038808 | L16: =I16*(1-settings!$B$6) -> 21.0364 | M16: 40 | N16: TRUE | O16: FALSE | P16: interpolated between 3 and 5 mm — not tested
A17: S235 | B17: 6 | C17: O2 | D17: per_m | E17: 4.5 | F17: 1 | G17: =G10+((6-5)/(8-5))*(G11-G10) -> 1.1368389 | H17: =H10+((6-5)/(8-5))*(H11-H10) -> 0.08932 | I17: =I10+((6-5)/(8-5))*(I11-I10) -> 28.523 | J17: =G17*(1-settings!$B$6) -> 0.79578722 | K17: =H17*(1-settings!$B$6) -> 0.062524 | L17: =I17*(1-settings!$B$6) -> 19.9661 | M17: 60 | N17: TRUE | O17: FALSE | P17: interpolated between 5 and 8 mm — not tested
A18: S235 | B18: 12 | C18: O2 | D18: per_m | E18: 1.7 | F18: 2 | G18: =G11+((12-8)/(10-8))*(G12-G11) -> 2.8173833 | H18: =H11+((12-8)/(10-8))*(H12-H11) -> 0.17556 | I18: =I12 -> 23.903 | J18: =G18*(1-settings!$B$6) -> 1.9721683 | K18: =H18*(1-settings!$B$6) -> 0.122892 | L18: =I18*(1-settings!$B$6) -> 16.7321 | M18: 120 | N18: TRUE | O18: FALSE | P18: extrapolated from 8–10 mm — not tested; verify in Sophia
A19: S235 | B19: 12.7 | C19: O2 | D19: per_m | E19: 1.5 | F19: 2.2 | G19: =G11+((12.7-8)/(10-8))*(G12-G11) -> 3.02498 | H19: =H11+((12.7-8)/(10-8))*(H12-H11) -> 0.185262 | I19: =I12 -> 23.903 | J19: =G19*(1-settings!$B$6) -> 2.117486 | K19: =H19*(1-settings!$B$6) -> 0.1296834 | L19: =I19*(1-settings!$B$6) -> 16.7321 | M19: 127 | N19: TRUE | O19: FALSE | P19: extrapolated from 8–10 mm — not tested; verify in Sophia
A21: Not covered: S235 1–2.5 mm (use the DC01 rows), 1.4301 and AlMg3 other than 1.5 mm, all tube-laser rows. The price per m here is the cutting-length part only; the area part (materials_price_bands) carries most of the price.

Sheet rate_finish
A1: rate_finish — deburring and engraving (NEW columns: setup_per_order_eur, min_part_mm)
A2: Deburr = edge breaking both sides. 247 refuses edge finishing below the minimum part size.
A4: code | B4: name | C4: unit | D4: price_sell (€) | E4: setup_per_order_sell (€) | F4: price_cost_at_margin (€) | G4: setup_per_order_cost_at_margin (€) | H4: rule / note
A5: deburr | B5: Edge breaking both sides | C5: m | D5: =247_base!$B$19*(1+settings!$B$5) -> 1.2903 | E5: =247_base!$B$18*(1+settings!$B$5) -> 36.828 | F5: =D5*(1-settings!$B$6) -> 0.90321 | G5: =E5*(1-settings!$B$6) -> 25.7796 | H5: Setup shared by the edge-broken parts in the order; per m of the part's cut length. Minimum part size: steel 250 × 60 or 600 × 50 mm; aluminium/stainless 50 × 50 mm.
A6: engrave | B6: Engrave part name | C6: part | D6: =247_base!$B$20*(1+settings!$B$5) -> 0.418 | E6: 0 | F6: =D6*(1-settings!$B$6) -> 0.2926 | G6: 0 | H6: 247 charges per part (name engraved), not per m — unit changes from m to part

Sheet rate_general
A1: rate_general — new and changed fields for the market rate version
A2: order_charge_eur and packaging are NEW columns. default_margin_pct stays for reporting only (see import_notes).
A4: field | B4: value_sell | C4: value_cost_at_margin | D4: note
A5: order_charge_eur | B5: =247_base!$B$17*(1+settings!$B$5) -> 17.886 | C5: =B5*(1-settings!$B$6) -> 12.5202 | D5: NEW — per order, shared by all part lines
A6: packaging_box_eur | B6: =247_base!$B$21*(1+settings!$B$5) -> 2.75 | C6: =B6*(1-settings!$B$6) -> 1.925 | D6: NEW — small orders
A7: packaging_pallet_eur | B7: =247_base!$B$22*(1+settings!$B$5) -> 34.43 | C7: =B7*(1-settings!$B$6) -> 24.101 | D7: NEW — orders with parts > ~600 mm or > ~25 kg
A8: default_margin_pct | B8: 30 | D8: Keep 30 — but in market mode it is a CHECK (1 − cost/price ≥ 30 %), not a markup on these rates
A9: labour_rate_eur_h | B9: 25 | D9: Michael's job-costing figure (placeholder in DB is 35)
A10: blank_margin_mm | B10: 0 | D10: Material priced on net mass — blank margin no longer used for price
A11: pricing_mode | B11: market | D11: NEW — market = rates are selling prices; cost = rates are costs with margin on top

Sheet rate_leadtime
A1: rate_leadtime — NEW table: price multiplier by promised lead time
A2: From 247 test 3 totals (38 parts). Applies to the whole order. 247 also offers up to 8 weeks ahead at a lower price — not tested.
A4: working_days | B4: multiplier | C4: source | D4: note
A5: 11 | B5: =247_base!$B$23 -> 1 | C5: 12 Oct base | D5: Multiply the whole order price (parts, setups, order charge). StretchMetal standard lead time is 10–15 working days = base.
A6: 7 | B6: =247_base!$B$24 -> 1.14 | C6: 6 Oct: +14 % | D6: Multiply the whole order price (parts, setups, order charge). StretchMetal standard lead time is 10–15 working days = base.
A7: 4 | B7: =247_base!$B$25 -> 1.711 | C7: 1 Oct: +71 % | D7: Multiply the whole order price (parts, setups, order charge). StretchMetal standard lead time is 10–15 working days = base.

Sheet import_notes
A1: How to load this into Supabase (quote.stretchmetal.pl) with Claude Code
A2: Sheet names = table names; column headers = column names. Columns marked NEW need a migration.
A4: # | B4: step | C4: detail
A5: 1 | B5: Create a rate version | C5: INSERT INTO rate_versions a row named settings!rate_version_name; copy all rate tables from the placeholder version into it, then apply the sheets below to the new version only. Keep the placeholder version untouched.
A6: 2 | B6: materials | C6: For each material_code set price_per_kg = the JSON bands from materials_price_bands (price_per_kg_sell), scrap_pct_default = 0, placeholder = false. CODE CHANGE: the material operation must use net mass (geometry.measures.massKg) instead of blank rectangle × (1 + scrap).
A7: 3 | B7: rate_laser | C7: Upsert rows (material_code, thickness_mm) with mode = per_m, price_per_m = price_per_m_sell, price_per_pierce = price_per_pierce_sell, gas, min_contour_mm, in_house = true, placeholder = false. MIGRATION: add column setup_eur numeric — charged once per material/thickness present in the quote and divided over the part lines of that material/thickness. Keep the slow-contour factor at 1.0 in this version (247 prices small holes at ≈ €0.02).
A8: 4 | B8: rate_finish | C8: Update deburr (price per m, unit m) and engrave (unit part). MIGRATION: add setup_per_order_eur numeric and min_part_mm text; deburr setup is divided over the edge-broken part lines; the tool must refuse deburring below the minimum size like Sophia does.
A9: 5 | B9: rate_general | C9: MIGRATION: add order_charge_eur, packaging_box_eur, packaging_pallet_eur numeric and pricing_mode text. In pricing_mode = market the quote price = Σ operations at these rates + setups + order charge (+ packaging) × lead-time multiplier; margin is computed afterwards as 1 − cost/price from the machine-hour cost model and shown as a check against default_margin_pct. Do NOT apply default_margin_pct on top of these rates.
A10: 6 | B10: rate_leadtime | C10: MIGRATION: new table (rate_version_id, working_days int, multiplier numeric). Quote builder picks the multiplier for the promised lead time; base = 11 working days.
A11: 7 | B11: Quote PDF | C11: Show the setups and order charge as separate lines or fold them into the part prices (247 folds them in). Packaging as a separate line.
A12: 8 | B12: Check | C12: Re-price SM-2026-0004 in the new version: every part should come out at 247 × 1.05 within ≈ €1 (see 247_pricelist.xlsx, Calculator sheet, for the actual 247 prices).
A13: 9 | B13: Not covered yet | C13: Bending, rolling, tube laser, welding, threads, powder coating — no 247 data. Bending and tube laser need STEP/TUB test files in Sophia. Until then keep the placeholder cost rates with 30 % margin for those operations.
